<?xml version="1.0" encoding="utf-8"?><items termsofuse="https://boardgamegeek.com/xmlapi/termsofuse"><item type="boardgame" id="243995">
         <thumbnail>https://cf.geekdo-images.com/oTFlkyst96AsKCcRX3a3mg__thumb/img/j84WOpgnLbM5NAltaW7Hy-akwlQ=/fit-in/200x150/filters:strip_icc()/pic7117479.jpg</thumbnail>
      <image>https://cf.geekdo-images.com/oTFlkyst96AsKCcRX3a3mg__original/img/QyfifwwmOPEmtcyOY7QzSlFNUog=/0x0/filters:format(jpeg)/pic7117479.jpg</image>
                                     				
				<name type="primary" sortindex="1" value="CompoundIt!" />
			
						                           
						               													<description>CompoundIt! is a word game in which the &amp;ldquo;letters&amp;rdquo; are chemical elements and the &amp;ldquo;words&amp;rdquo; are compounds. The rules of the game strive to balance entertainment and playability, scientific accuracy, and educational value. The target audience includes students, science enthusiasts, nerds, and word game fans interested in learning an entirely new &amp;ldquo;language&amp;rdquo;. The style of play is familiar to those who have played other crossword-style board games, and the rules for compound formation come from chemistry itself.&amp;#10;&amp;#10;Players make moves using a hand of ten tiles. Each tile is an element from the periodic table, although not every element is represented--only those found in relatively common compounds. A valid move creates a neutral compound with balanced charges. Compounds may be either binary (like carbon dioxide, methane, water, or ammonia) or involve polyatomic ions (sulfate, nitrate, hydroxide, etc.) Subsequent turns build new compounds using both new tiles and tiles already on the board. Players score points based on the point value of each tile (some elements are worth more than others), whether they are utilized in one direction or both horizontally and vertically, and whether they are played on special bonus squares. The game ends when one player runs out of tiles following the exhaustion of the general supply; at this time, the player with the most points wins.&amp;#10;&amp;#10;</description>
										      	               				<yearpublished value="2018" />
						               				<minplayers value="2" />
						               				<maxplayers value="4" />
						      			<poll name="suggested_numplayers" title="User Suggested Number of Players" totalvotes="0">
			
		<results numplayers="1">		
					<result value="Best" numvotes="0" />
					<result value="Recommended" numvotes="0" />
					<result value="Not Recommended" numvotes="0" />
				</results>					
			
		<results numplayers="2">		
					<result value="Best" numvotes="0" />
					<result value="Recommended" numvotes="0" />
					<result value="Not Recommended" numvotes="0" />
				</results>					
			
		<results numplayers="3">		
					<result value="Best" numvotes="0" />
					<result value="Recommended" numvotes="0" />
					<result value="Not Recommended" numvotes="0" />
				</results>					
			
		<results numplayers="4">		
					<result value="Best" numvotes="0" />
					<result value="Recommended" numvotes="0" />
					<result value="Not Recommended" numvotes="0" />
				</results>					
			
		<results numplayers="4+">		
					<result value="Best" numvotes="0" />
					<result value="Recommended" numvotes="0" />
					<result value="Not Recommended" numvotes="0" />
				</results>					
	</poll> 			               				<playingtime value="90" />
						               				<minplaytime value="45" />
						               				<maxplaytime value="90" />
						               				<minage value="12" />
						      			<poll name="suggested_playerage" title="User Suggested Player Age" totalvotes="0">
			<results>		
					<result value="2" numvotes="0" />
					<result value="3" numvotes="0" />
					<result value="4" numvotes="0" />
					<result value="5" numvotes="0" />
					<result value="6" numvotes="0" />
					<result value="8" numvotes="0" />
					<result value="10" numvotes="0" />
					<result value="12" numvotes="0" />
					<result value="14" numvotes="0" />
					<result value="16" numvotes="0" />
					<result value="18" numvotes="0" />
					<result value="21 and up" numvotes="0" />
				</results>					
	</poll> 			      			<poll name="language_dependence" title="Language Dependence" totalvotes="0">
			
		<results>		
					<result level="86" value="No necessary in-game text" numvotes="0" />
					<result level="87" value="Some necessary text - easily memorized or small crib sheet" numvotes="0" />
					<result level="88" value="Moderate in-game text - needs crib sheet or paste ups" numvotes="0" />
					<result level="89" value="Extensive use of text - massive conversion needed to be playable" numvotes="0" />
					<result level="90" value="Unplayable in another language" numvotes="0" />
				</results>					
	</poll> 			      			 			      				
		 			

			
		
					<link type="boardgamecategory" id="1094" value="Educational" />
		
									
				
		 			

			
		
					<link type="boardgamecategory" id="1025" value="Word Game" />
		
									
			

			      				
		 			

			
		
					<link type="boardgamemechanic" id="2040" value="Hand Management" />
		
									
				
		 			

			
		
					<link type="boardgamemechanic" id="2002" value="Tile Placement" />
		
									
			

			      				
		 			

			
		
					<link type="boardgamefamily" id="8374" value="Crowdfunding: Kickstarter" />
		
									
			

			      			

			      			

			      			

			      			

			      			

			      			

			      			

			      			

			      	      	      				
		 			

			
		
					<link type="boardgamedesigner" id="106229" value="Andrew Lyman-Buttler" />
		
									
			

			      				
		 			

			
		
					<link type="boardgameartist" id="106230" value="Melissa Lyman" />
		
									
			

			      	      				
		 			

			
		
					<link type="boardgamepublisher" id="38322" value="Bouncy Castle Games" />
		
									
			

			
	

	

	
	
	
   		<statistics page="1">
								<ratings >
			<usersrated value="0" />
			<average value="0" />
			<bayesaverage value="0" />

			<ranks>
															<rank type="subtype" id="1" name="boardgame" friendlyname="Board Game Rank" value="Not Ranked" bayesaverage="Not Ranked" />
												</ranks>

			<stddev value="0" />
			<median value="0" />
			<owned value="5" />
			<trading value="0" />
			<wanting value="1" />
			<wishing value="1" />
			<numcomments value="2" />
			<numweights value="0" />
			<averageweight value="0" />
			</ratings>
								</statistics>
     
	
          
</item>
</items>