<?xml version="1.0" encoding="utf-8"?><items termsofuse="https://boardgamegeek.com/xmlapi/termsofuse"><item type="boardgameexpansion" id="307119">
         <thumbnail>https://cf.geekdo-images.com/ubDdsCYBvyOTxGy6MegzGg__thumb/img/D6KyOWg7XLBxcexj1LyFcO9wxys=/fit-in/200x150/filters:strip_icc()/pic5345697.jpg</thumbnail>
      <image>https://cf.geekdo-images.com/ubDdsCYBvyOTxGy6MegzGg__original/img/mlOK-Ep-J_XgEY_UJLSeCjh2sD8=/0x0/filters:format(jpeg)/pic5345697.jpg</image>
                                     				
				<name type="primary" sortindex="1" value="Greedy Gifts of the Guildmasters: Patrons and Adventures for Parties of all Levels, for Four Against Darkness" />
			
						                           
						               													<description>Patrons Book for Four Against Darkness&amp;#10;&amp;#10;What is thy Bidding, my Master?&amp;#10;Tired of threading dungeons without a purpose? Try serving a patron! Within these pages, you will find twelve unique individuals eager to offer your adventurers special quests and rewards, expert skills, rules twists and unique benefits for the meager price of serving their machiavellian agendas. They might even join your party!&amp;#10;Also featuring nine mini-dungeons, character traits, gear, skills and rules and the Damsel-in-Distress and Fiendingo classes.&amp;#10;&amp;#10;Using this book requires only Four Against Darkness. However, it references most other books and contains information allowing it to be integrated with them.&amp;#10;&amp;#10;Intended for mature audiences and expert players.&amp;#10;&amp;#10;&amp;mdash;description from the publisher&amp;#10;&amp;#10;</description>
										      	               				<yearpublished value="2020" />
						               				<minplayers value="1" />
						               				<maxplayers value="4" />
						      			<poll name="suggested_numplayers" title="User Suggested Number of Players" totalvotes="0">
			
		<results numplayers="1">		
					<result value="Best" numvotes="0" />
					<result value="Recommended" numvotes="0" />
					<result value="Not Recommended" numvotes="0" />
				</results>					
			
		<results numplayers="2">		
					<result value="Best" numvotes="0" />
					<result value="Recommended" numvotes="0" />
					<result value="Not Recommended" numvotes="0" />
				</results>					
			
		<results numplayers="3">		
					<result value="Best" numvotes="0" />
					<result value="Recommended" numvotes="0" />
					<result value="Not Recommended" numvotes="0" />
				</results>					
			
		<results numplayers="4">		
					<result value="Best" numvotes="0" />
					<result value="Recommended" numvotes="0" />
					<result value="Not Recommended" numvotes="0" />
				</results>					
			
		<results numplayers="4+">		
					<result value="Best" numvotes="0" />
					<result value="Recommended" numvotes="0" />
					<result value="Not Recommended" numvotes="0" />
				</results>					
	</poll> 			               				<playingtime value="75" />
						               				<minplaytime value="45" />
						               				<maxplaytime value="75" />
						               				<minage value="0" />
						      			<poll name="suggested_playerage" title="User Suggested Player Age" totalvotes="0">
			<results>		
					<result value="2" numvotes="0" />
					<result value="3" numvotes="0" />
					<result value="4" numvotes="0" />
					<result value="5" numvotes="0" />
					<result value="6" numvotes="0" />
					<result value="8" numvotes="0" />
					<result value="10" numvotes="0" />
					<result value="12" numvotes="0" />
					<result value="14" numvotes="0" />
					<result value="16" numvotes="0" />
					<result value="18" numvotes="0" />
					<result value="21 and up" numvotes="0" />
				</results>					
	</poll> 			      			<poll name="language_dependence" title="Language Dependence" totalvotes="0">
			
		<results>		
					<result level="131" value="No necessary in-game text" numvotes="0" />
					<result level="132" value="Some necessary text - easily memorized or small crib sheet" numvotes="0" />
					<result level="133" value="Moderate in-game text - needs crib sheet or paste ups" numvotes="0" />
					<result level="134" value="Extensive use of text - massive conversion needed to be playable" numvotes="0" />
					<result level="135" value="Unplayable in another language" numvotes="0" />
				</results>					
	</poll> 			      			 			      				
		 			

			
		
					<link type="boardgamecategory" id="1042" value="Expansion for Base-game" />
		
									
				
		 			

			
		
					<link type="boardgamecategory" id="1022" value="Adventure" />
		
									
				
		 			

			
		
					<link type="boardgamecategory" id="1117" value="Book" />
		
									
				
		 			

			
		
					<link type="boardgamecategory" id="1020" value="Exploration" />
		
									
				
		 			

			
		
					<link type="boardgamecategory" id="1010" value="Fantasy" />
		
									
				
		 			

			
		
					<link type="boardgamecategory" id="1120" value="Print &amp; Play" />
		
									
			

			      				
		 			

			
		
					<link type="boardgamemechanic" id="2072" value="Dice Rolling" />
		
									
				
		 			

			
		
					<link type="boardgamemechanic" id="2055" value="Paper-and-Pencil" />
		
									
				
		 			

			
		
					<link type="boardgamemechanic" id="2819" value="Solo / Solitaire Game" />
		
									
			

			      				
		 			

			
		
					<link type="boardgamefamily" id="48895" value="Game: Four Against Darkness" />
		
									
			

			      			

			      				
		 			

			
		
					<link type="boardgameexpansion" id="197097" value="Four Against Darkness" inbound="true"/>
		
									
			

			      			

			      			

			      			

			      			

			      			

			      			

			      	      	      				
		 			

			
		
					<link type="boardgamedesigner" id="16254" value="Erick N. Bouchard" />
		
									
				
		 			

			
		
					<link type="boardgamedesigner" id="9056" value="Andrea Sfiligoi" />
		
									
			

			      				
		 			

			
		
					<link type="boardgameartist" id="117785" value="Ulysse Bouchard" />
		
									
				
		 			

			
		
					<link type="boardgameartist" id="9056" value="Andrea Sfiligoi" />
		
									
			

			      	      				
		 			

			
		
					<link type="boardgamepublisher" id="7993" value="Ganesha Games" />
		
									
			

			
	

	

	
	
	
   		<statistics page="1">
								<ratings >
			<usersrated value="9" />
			<average value="8" />
			<bayesaverage value="0" />

			<ranks>
															<rank type="subtype" id="1" name="boardgame" friendlyname="Board Game Rank" value="Not Ranked" bayesaverage="Not Ranked" />
												</ranks>

			<stddev value="1.1547" />
			<median value="0" />
			<owned value="65" />
			<trading value="0" />
			<wanting value="3" />
			<wishing value="21" />
			<numcomments value="7" />
			<numweights value="0" />
			<averageweight value="0" />
			</ratings>
								</statistics>
     
	
          
</item>
</items>