<?xml version="1.0" encoding="utf-8"?><items termsofuse="https://boardgamegeek.com/xmlapi/termsofuse"><item type="boardgame" id="40765">
         <thumbnail>https://cf.geekdo-images.com/XHTMyEGDsNHLKXkbGDKaKA__thumb/img/mf5yep4EN9ZQP5hId2GsPB9zduo=/fit-in/200x150/filters:strip_icc()/pic1351042.jpg</thumbnail>
      <image>https://cf.geekdo-images.com/XHTMyEGDsNHLKXkbGDKaKA__original/img/GKb17ffVsXR5RFKmKE5OTT8O21U=/0x0/filters:format(jpeg)/pic1351042.jpg</image>
                                     				
				<name type="primary" sortindex="1" value="Clash of Cultures" />
			
						                           
						               													<description>From Christian Marcussen, the creator of Merchants and Marauders, comes Clash of Cultures, a civilization game in which each player leads a civilization from a single settlement to a mighty empire. Players must explore their surroundings, build large cities, research advances and conquer those who stand in the way. The game features a modular board for players to explore, 48 distinct advances, seven mighty wonders, and loads of miniatures and cards. The winner will create a culture that will be remembered and admired for millennia.&amp;#10;&amp;#10;Advances&amp;#10;The game features about 48 distinct advances. The whole &amp;quot;tech-tree&amp;quot; is very flexible with no dead ends, yet still intuitive, sensible and &amp;quot;realistic.&amp;quot; Additionally you have a great overview of what advances other cultures have - no need to ask - just look.&amp;#10;&amp;#10;Modular Board&amp;#10;Players start with a civilization in its infancy. Move settlers to uncharted regions and reveal the terrain and its resources. Several mechanisms have been implemented to assure that an unlucky placement of region-tiles won't be a decider.&amp;#10;&amp;#10;Playing Time&amp;#10;The game covers a time span similar to AH Civilization - that is to pre-gunpowder. This epic game is playable in about an hour per player! This is a pretty good playing time for a game that covers so much ground as this game will.&amp;#10;&amp;#10;City management&amp;#10;Players expand their cities through the game. But not just to the generic larger city. Players instead choose a building type which represents the growth of the city. For instance you can expand a city with a port, fort, temple and academy - all with different benefits! Additionally cities can be &amp;quot;angry,&amp;quot; &amp;quot;neutral&amp;quot; and &amp;quot;happy.&amp;quot; Everything integrated in an intuitive and elegant fashion.&amp;#10;&amp;#10;Multiple paths to victory&amp;#10;Earn points through:&amp;#10;- Founding cities and increasing their sizes&amp;#10;- Advances&amp;#10;- Objectives &amp;#10;- Wonders&amp;#10;- Events&amp;#10;&amp;#10;</description>
										      	               				<yearpublished value="2012" />
						               				<minplayers value="2" />
						               				<maxplayers value="4" />
						      			<poll name="suggested_numplayers" title="User Suggested Number of Players" totalvotes="134">
			
		<results numplayers="1">		
					<result value="Best" numvotes="0" />
					<result value="Recommended" numvotes="1" />
					<result value="Not Recommended" numvotes="80" />
				</results>					
			
		<results numplayers="2">		
					<result value="Best" numvotes="26" />
					<result value="Recommended" numvotes="64" />
					<result value="Not Recommended" numvotes="20" />
				</results>					
			
		<results numplayers="3">		
					<result value="Best" numvotes="62" />
					<result value="Recommended" numvotes="49" />
					<result value="Not Recommended" numvotes="7" />
				</results>					
			
		<results numplayers="4">		
					<result value="Best" numvotes="74" />
					<result value="Recommended" numvotes="44" />
					<result value="Not Recommended" numvotes="3" />
				</results>					
			
		<results numplayers="4+">		
					<result value="Best" numvotes="0" />
					<result value="Recommended" numvotes="1" />
					<result value="Not Recommended" numvotes="61" />
				</results>					
	</poll> 			               				<playingtime value="240" />
						               				<minplaytime value="180" />
						               				<maxplaytime value="240" />
						               				<minage value="14" />
						      			<poll name="suggested_playerage" title="User Suggested Player Age" totalvotes="32">
			<results>		
					<result value="2" numvotes="0" />
					<result value="3" numvotes="0" />
					<result value="4" numvotes="0" />
					<result value="5" numvotes="0" />
					<result value="6" numvotes="0" />
					<result value="8" numvotes="0" />
					<result value="10" numvotes="2" />
					<result value="12" numvotes="10" />
					<result value="14" numvotes="18" />
					<result value="16" numvotes="2" />
					<result value="18" numvotes="0" />
					<result value="21 and up" numvotes="0" />
				</results>					
	</poll> 			      			<poll name="language_dependence" title="Language Dependence" totalvotes="40">
			
		<results>		
					<result level="641" value="No necessary in-game text" numvotes="0" />
					<result level="642" value="Some necessary text - easily memorized or small crib sheet" numvotes="0" />
					<result level="643" value="Moderate in-game text - needs crib sheet or paste ups" numvotes="5" />
					<result level="644" value="Extensive use of text - massive conversion needed to be playable" numvotes="33" />
					<result level="645" value="Unplayable in another language" numvotes="2" />
				</results>					
	</poll> 			      			 			      				
		 			

			
		
					<link type="boardgamecategory" id="1050" value="Ancient" />
		
									
				
		 			

			
		
					<link type="boardgamecategory" id="1029" value="City Building" />
		
									
				
		 			

			
		
					<link type="boardgamecategory" id="1015" value="Civilization" />
		
									
				
		 			

			
		
					<link type="boardgamecategory" id="1021" value="Economic" />
		
									
				
		 			

			
		
					<link type="boardgamecategory" id="1020" value="Exploration" />
		
									
				
		 			

			
		
					<link type="boardgamecategory" id="1086" value="Territory Building" />
		
									
			

			      				
		 			

			
		
					<link type="boardgamemechanic" id="2001" value="Action Points" />
		
									
				
		 			

			
		
					<link type="boardgamemechanic" id="2080" value="Area Majority / Influence" />
		
									
				
		 			

			
		
					<link type="boardgamemechanic" id="2072" value="Dice Rolling" />
		
									
				
		 			

			
		
					<link type="boardgamemechanic" id="2676" value="Grid Movement" />
		
									
				
		 			

			
		
					<link type="boardgamemechanic" id="2040" value="Hand Management" />
		
									
				
		 			

			
		
					<link type="boardgamemechanic" id="2026" value="Hexagon Grid" />
		
									
				
		 			

			
		
					<link type="boardgamemechanic" id="2011" value="Modular Board" />
		
									
				
		 			

			
		
					<link type="boardgamemechanic" id="2849" value="Tech Trees / Tech Tracks" />
		
									
				
		 			

			
		
					<link type="boardgamemechanic" id="2008" value="Trading" />
		
									
			

			      				
		 			

			
		
					<link type="boardgamefamily" id="25158" value="Components: Miniatures" />
		
									
				
		 			

			
		
					<link type="boardgamefamily" id="75747" value="Game: Clash of Cultures" />
		
									
				
		 			

			
		
					<link type="boardgamefamily" id="12210" value="Mechanism: 4X" />
		
									
			

			      				
		 			

			
		
					<link type="boardgameexpansion" id="146244" value="Clash of Cultures: Civilizations" />
		
									
				
		 			

			
		
					<link type="boardgameexpansion" id="167825" value="Clash of Cultures: Civilizations – Aztecs" />
		
									
			

			      			

			      			

			      			

			      			

			      			

			      				
		 			

			
		
					<link type="boardgameimplementation" id="299659" value="Clash of Cultures: Monumental Edition" />
		
									
			

			      			

			      	      	      				
		 			

			
		
					<link type="boardgamedesigner" id="7614" value="Christian Marcussen" />
		
									
			

			      				
		 			

			
		
					<link type="boardgameartist" id="14057" value="Chris Quilliams" />
		
									
			

			      	      				
		 			

			
		
					<link type="boardgamepublisher" id="5657" value="Filosofia Éditions" />
		
									
				
		 			

			
		
					<link type="boardgamepublisher" id="538" value="Z-Man Games" />
		
									
				
		 			

			
		
					<link type="boardgamepublisher" id="24883" value="Ediciones MasQueOca" />
		
									
				
		 			

			
		
					<link type="boardgamepublisher" id="29895" value="Frosted Games" />
		
									
				
		 			

			
		
					<link type="boardgamepublisher" id="39" value="Pegasus Spiele" />
		
									
			

			
	

	

	
	
	
   		<statistics page="1">
								<ratings >
			<usersrated value="5670" />
			<average value="7.58171" />
			<bayesaverage value="7.02544" />

			<ranks>
															<rank type="subtype" id="1" name="boardgame" friendlyname="Board Game Rank" value="414" bayesaverage="7.02544" />
																				<rank type="family" id="5497" name="strategygames" friendlyname="Strategy Game Rank" value="244" bayesaverage="7.14517" />
												</ranks>

			<stddev value="1.42889" />
			<median value="0" />
			<owned value="6335" />
			<trading value="293" />
			<wanting value="391" />
			<wishing value="2374" />
			<numcomments value="1394" />
			<numweights value="361" />
			<averageweight value="3.5956" />
			</ratings>
								</statistics>
     
	
          
</item>
</items>