<?xml version="1.0" encoding="utf-8"?><items termsofuse="https://boardgamegeek.com/xmlapi/termsofuse"><item type="boardgame" id="7806">
         <thumbnail>https://cf.geekdo-images.com/6CqaLFREj_a_YlFUdLYzGA__thumb/img/n-dayYeEzZdr8Gu-taigmY0KYv4=/fit-in/200x150/filters:strip_icc()/pic3297261.png</thumbnail>
      <image>https://cf.geekdo-images.com/6CqaLFREj_a_YlFUdLYzGA__original/img/jlXAJVSP-9XCbOvsyEpm4gTShkg=/0x0/filters:format(png)/pic3297261.png</image>
                                     				
				<name type="primary" sortindex="1" value="King Up!" />
			
						                               				
				<name type="alternate" sortindex="1" value="King Me!" />
			    				
				<name type="alternate" sortindex="1" value="Viva il Re!" />
			    				
				<name type="alternate" sortindex="1" value="Vive le Roi" />
			    				
				<name type="alternate" sortindex="1" value="¡Viva el Rey!" />
			    				
				<name type="alternate" sortindex="1" value="Царь Горы" />
			    				
				<name type="alternate" sortindex="1" value="封王" />
			    				
				<name type="alternate" sortindex="1" value="造王者！" />
			
						               													<description>From the publisher:&amp;#10;&amp;#10;With the announcement of the King's retirement, the pirouette for succession begins! All of his subjects from cobbler to cook, painter to paladin, debutante to duchess bustle about the castle in preparation for the succession. One of your favorites can attain the throne. But, beware! It will require clever maneuvering and selective positioning to be in the right place at the right time to achieve the crown!&amp;#10;&amp;#10;From the box:&amp;#10;&amp;#10;The King has retired! Paladins, cooks, painters and all the other subjects in the kingdom bustle about for the succession. Play your cards right and bring your favorite to the throne!&amp;#10;&amp;#10;From the rules:&amp;#10;&amp;#10;Long live the king! A bluff and deduction game for 3-6 players, age 8 and up. The enlightened monarch Vladimir Miritiro, tired of reigning, has decided to choose his successor among his subjects. The players are helping him in this decision by advising their favorites and trying to crown one of them as the new king.&amp;#10;&amp;#10;</description>
										      	               				<yearpublished value="2004" />
						               				<minplayers value="3" />
						               				<maxplayers value="6" />
						      			<poll name="suggested_numplayers" title="User Suggested Number of Players" totalvotes="35">
			
		<results numplayers="1">		
					<result value="Best" numvotes="0" />
					<result value="Recommended" numvotes="0" />
					<result value="Not Recommended" numvotes="24" />
				</results>					
			
		<results numplayers="2">		
					<result value="Best" numvotes="0" />
					<result value="Recommended" numvotes="2" />
					<result value="Not Recommended" numvotes="20" />
				</results>					
			
		<results numplayers="3">		
					<result value="Best" numvotes="1" />
					<result value="Recommended" numvotes="17" />
					<result value="Not Recommended" numvotes="10" />
				</results>					
			
		<results numplayers="4">		
					<result value="Best" numvotes="11" />
					<result value="Recommended" numvotes="18" />
					<result value="Not Recommended" numvotes="0" />
				</results>					
			
		<results numplayers="5">		
					<result value="Best" numvotes="21" />
					<result value="Recommended" numvotes="9" />
					<result value="Not Recommended" numvotes="0" />
				</results>					
			
		<results numplayers="6">		
					<result value="Best" numvotes="13" />
					<result value="Recommended" numvotes="15" />
					<result value="Not Recommended" numvotes="2" />
				</results>					
			
		<results numplayers="6+">		
					<result value="Best" numvotes="0" />
					<result value="Recommended" numvotes="0" />
					<result value="Not Recommended" numvotes="16" />
				</results>					
	</poll> 			               				<playingtime value="30" />
						               				<minplaytime value="30" />
						               				<maxplaytime value="30" />
						               				<minage value="8" />
						      			<poll name="suggested_playerage" title="User Suggested Player Age" totalvotes="10">
			<results>		
					<result value="2" numvotes="0" />
					<result value="3" numvotes="0" />
					<result value="4" numvotes="0" />
					<result value="5" numvotes="0" />
					<result value="6" numvotes="2" />
					<result value="8" numvotes="7" />
					<result value="10" numvotes="1" />
					<result value="12" numvotes="0" />
					<result value="14" numvotes="0" />
					<result value="16" numvotes="0" />
					<result value="18" numvotes="0" />
					<result value="21 and up" numvotes="0" />
				</results>					
	</poll> 			      			<poll name="language_dependence" title="Language Dependence" totalvotes="15">
			
		<results>		
					<result level="1" value="No necessary in-game text" numvotes="15" />
					<result level="2" value="Some necessary text - easily memorized or small crib sheet" numvotes="0" />
					<result level="3" value="Moderate in-game text - needs crib sheet or paste ups" numvotes="0" />
					<result level="4" value="Extensive use of text - massive conversion needed to be playable" numvotes="0" />
					<result level="5" value="Unplayable in another language" numvotes="0" />
				</results>					
	</poll> 			      			 			      				
		 			

			
		
					<link type="boardgamecategory" id="1023" value="Bluffing" />
		
									
				
		 			

			
		
					<link type="boardgamecategory" id="1039" value="Deduction" />
		
									
				
		 			

			
		
					<link type="boardgamecategory" id="1070" value="Renaissance" />
		
									
			

			      				
		 			

			
		
					<link type="boardgamemechanic" id="2017" value="Voting" />
		
									
			

			      				
		 			

			
		
					<link type="boardgamefamily" id="22783" value="Admin: Better Description Needed!" />
		
									
				
		 			

			
		
					<link type="boardgamefamily" id="59705" value="Misc: LongPack Games" />
		
									
			

			      				
		 			

			
		
					<link type="boardgameexpansion" id="57883" value="King Me! The Toilet" />
		
									
			

			      			

			      			

			      			

			      			

			      			

			      				
		 			

			
		
					<link type="boardgameimplementation" id="254191" value="Dragon Ball Z Power Up! Board Game" />
		
									
				
		 			

			
		
					<link type="boardgameimplementation" id="224907" value="Super Mario: Level Up! Board Game" />
		
									
			

			      			

			      	      	      				
		 			

			
		
					<link type="boardgamedesigner" id="2729" value="Stefano Luperto" />
		
									
			

			      				
		 			

			
		
					<link type="boardgameartist" id="12671" value="Daniele Barletta" />
		
									
				
		 			

			
		
					<link type="boardgameartist" id="12692" value="David Cochard" />
		
									
			

			      	      				
		 			

			
		
					<link type="boardgamepublisher" id="917" value="DV Games" />
		
									
				
		 			

			
		
					<link type="boardgamepublisher" id="2973" value="Edge Entertainment" />
		
									
				
		 			

			
		
					<link type="boardgamepublisher" id="18852" value="Hobby World" />
		
									
				
		 			

			
		
					<link type="boardgamepublisher" id="15983" value="Jolly Thinkers" />
		
									
				
		 			

			
		
					<link type="boardgamepublisher" id="10" value="Mayfair Games" />
		
									
				
		 			

			
		
					<link type="boardgamepublisher" id="34" value="Ravensburger" />
		
									
				
		 			

			
		
					<link type="boardgamepublisher" id="9234" value="Swan Panasia Co., Ltd." />
		
									
				
		 			

			
		
					<link type="boardgamepublisher" id="42" value="Tilsit" />
		
									
				
		 			

			
		
					<link type="boardgamepublisher" id="35809" value="Zhiyanjia" />
		
									
			

			
	

	

	
	
	
   		<statistics page="1">
								<ratings >
			<usersrated value="2225" />
			<average value="6.39338" />
			<bayesaverage value="5.96231" />

			<ranks>
															<rank type="subtype" id="1" name="boardgame" friendlyname="Board Game Rank" value="2958" bayesaverage="5.96231" />
																				<rank type="family" id="5499" name="familygames" friendlyname="Family Game Rank" value="942" bayesaverage="6.04173" />
												</ranks>

			<stddev value="1.21725" />
			<median value="0" />
			<owned value="2402" />
			<trading value="110" />
			<wanting value="33" />
			<wishing value="227" />
			<numcomments value="692" />
			<numweights value="204" />
			<averageweight value="1.2157" />
			</ratings>
								</statistics>
     
	
          
</item>
</items>